karrio/mappers/hay_post/__init__.py
karrio/mappers/hay_post/mapper.py
karrio/mappers/hay_post/proxy.py
karrio/mappers/hay_post/settings.py
karrio/plugins/hay_post/__init__.py
karrio/providers/hay_post/__init__.py
karrio/providers/hay_post/error.py
karrio/providers/hay_post/rate.py
karrio/providers/hay_post/tracking.py
karrio/providers/hay_post/units.py
karrio/providers/hay_post/utils.py
karrio/providers/hay_post/shipment/__init__.py
karrio/providers/hay_post/shipment/create.py
karrio/schemas/hay_post/__init__.py
karrio/schemas/hay_post/auth_request.py
karrio/schemas/hay_post/auth_response.py
karrio/schemas/hay_post/error.py
karrio/schemas/hay_post/order_create_request.py
karrio/schemas/hay_post/order_create_response.py
karrio/schemas/hay_post/order_tracking_request.py
karrio/schemas/hay_post/order_tracking_response.py
karrio/schemas/hay_post/tariff_request.py
karrio_hay_post-2026.1.4.dist-info/METADATA
karrio_hay_post-2026.1.4.dist-info/WHEEL
karrio_hay_post-2026.1.4.dist-info/entry_points.txt
karrio_hay_post-2026.1.4.dist-info/top_level.txt
karrio_hay_post-2026.1.4.dist-info/RECORD
